caterpillar_api/__init__.py
caterpillar_api/monarch.py
caterpillar_api/util.py
caterpillar_api-1.63.dist-info/LICENSE
caterpillar_api-1.63.dist-info/METADATA
caterpillar_api-1.63.dist-info/WHEEL
caterpillar_api-1.63.dist-info/top_level.txt
caterpillar_api-1.63.dist-info/RECORD
